setup.py
socialknife/__init__.py
socialknife.egg-info/PKG-INFO
socialknife.egg-info/SOURCES.txt
socialknife.egg-info/dependency_links.txt
socialknife.egg-info/requires.txt
socialknife.egg-info/top_level.txt