Metadata-Version: 2.1
Name: socialknife
Version: 0.0.1
Summary: Socialblade api wrapper
Home-page: https://github.com/eliseomartelli/SocialKnife
Author: Eliseo Martelli
Author-email: me@eliseomartelli.it
License: UNKNOWN
Platform: UNKNOWN
